importance_cross_entropy/__init__.py
importance_cross_entropy/loss.py
importance_cross_entropy/metrics.py
importance_cross_entropy-0.0.1.dist-info/licenses/LICENSE
importance_cross_entropy-0.0.1.dist-info/WHEEL
importance_cross_entropy-0.0.1.dist-info/METADATA
importance_cross_entropy-0.0.1.dist-info/RECORD
