Metadata-Version: 2.4
Name: importance_cross_entropy
Version: 0.0.1
Summary: Tensorflow implementation of the Importance Cross Entropy Loss function pruposed on this paper: https://www.cv-foundation.org/openaccess/content_cvpr_2016/papers/Niu_Ordinal_Regression_With_CVPR_2016_paper.pdf. Custom metrics were built for MAPE, MAE, and Accuracy. Two loss functions were create one that includes the lambda calculation and one that doesn't. (repository author: Pedro Jose Carrinho Ribeiro; pedro-carrinho@hotmail.com pedro.carrinho @inl.com).
Author: Pedro Jose Carrinho Ribeiro
Requires-Python: ~=3.10.0
Classifier: Programming Language :: Python :: 3
Classifier: License :: OSI Approved :: MIT License
License-File: LICENSE
